PS/2/rom.v
module rom (
    input        clk,
    input        rst_n,
    input  [4:0] addr,
    output [7:0] seg   
);

    reg [7:0] rom[16:0];
    integer i;
    always @(posedge clk) begin
      if(!rst_n)
        begin
          rom[0] <= 8'b1111_1100;
          rom[1] <= 8'b0110_0000;
          rom[2] <= 8'b1101_1010;
          rom[3] <= 8'b1111_0010;
          rom[4] <= 8'b0110_0110;
          rom[5] <= 8'b1011_0110;
          rom[6] <= 8'b1011_1110;
          rom[7] <= 8'b1110_0000;
          rom[8] <= 8'b1111_1110;
          rom[9] <= 8'b1111_0110;
          rom[10]<= 8'b1110_1110;
          rom[11]<= 8'b1111_1110;
          rom[12]<= 8'b1001_1100;
          rom[13]<= 8'b1111_1100;
          rom[14]<= 8'b1001_1110;
          rom[15]<= 8'b1000_1110;
          rom[16]<= 8'b0000_0000;
        end
        else begin
          for (i = 0;i < 16 ;i = i + 1) begin
            rom[i] <= rom[i];
          end
        end
    end

    assign seg = rst_n ? rom[addr] : 0;
    
endmodule //rom

example/rom_ascii.v
module rom_ascii(
    input        clk,
    input        rst_n,
    input  [7:0] data,
    output [7:0] seg1,
    output [7:0] seg2
);
    reg [15:0] lut [35:0];
    integer i;
    always @(posedge clk) begin
      if(!rst_n)
        begin
              lut[0] <= {8'h45,8'h30};
              lut[1] <= {8'h16,8'h31};
              lut[2] <= {8'h1E,8'h32};
              lut[3] <= {8'h26,8'h33};
              lut[4] <= {8'h25,8'h34};
              lut[5] <= {8'h2E,8'h35};
              lut[6] <= {8'h36,8'h36};
              lut[7] <= {8'h3D,8'h37};
              lut[8] <= {8'h3E,8'h38};
              lut[9] <= {8'h46,8'h39};

              lut[10]<= {8'h1C,8'h41};
              lut[11]<= {8'h32,8'h42};
              lut[12]<= {8'h21,8'h43};
              lut[13]<= {8'h23,8'h44};
              lut[14]<= {8'h24,8'h45};
              lut[15]<= {8'h2B,8'h46};
              lut[16]<= {8'h34,8'h47};
              lut[17]<= {8'h33,8'h48};
              lut[18]<= {8'h43,8'h49};
              lut[19]<= {8'h3B,8'h4A};
              lut[20]<= {8'h42,8'h4B};
              lut[21]<= {8'h4B,8'h4C};
              lut[22]<= {8'h3A,8'h4D};
              lut[23]<= {8'h31,8'h4E};
              lut[24]<= {8'h44,8'h4f};
              lut[25]<= {8'h4d,8'h50};
              lut[26]<= {8'h15,8'h51};
              lut[27]<= {8'h2d,8'h52};
              lut[28]<= {8'h1b,8'h53};
              lut[29]<= {8'h2c,8'h54};
              lut[30]<= {8'h3c,8'h55};
              lut[31]<= {8'h2a,8'h56};
              lut[32]<= {8'h1d,8'h57};
              lut[33]<= {8'h22,8'h58};
              lut[34]<= {8'h35,8'h59};
              lut[35]<= {8'h1a,8'h5a};
        end
        else begin
          for(i = 0;i<36;i=i+1)begin
            lut[i] <= lut[i];
          end
        end
    end

    wire [7:0] lut_key [35:0];
    wire [7:0] lut_data[35:0];
    reg [7:0] lut_out;
    reg [7:0] addr;
    genvar n;
    generate
        for(n = 0;n<36; n = n + 1)begin
            assign lut_key[n][7:0] = lut[n][15:8];
            assign lut_data[n][7:0] = lut[n][7:0];
        end
    endgenerate


    always @(*) begin
        lut_out = 0;
        for(i = 0;i<36;i=i+1)begin
            lut_out = lut_out | ({8{lut_key[i] == data}} & lut_data[i]);
        end
        // addr1 = {data != 0 && data != 'hF0 && buffer != 'hF0} ?  {1'd0,lut_out[3:0]} : 5'd16;
        // addr2 = {data != 0 && data != 'hF0 && buffer != 'hF0} ?  {1'd0,lut_out[7:4]} : 5'd16;
    end

    reg  [7:0] tmp;
    reg  [7:0] buffer;
    always @(posedge clk or negedge rst_n) begin
      if(!rst_n)
        begin
          buffer <= 0;
          tmp <= 0;
        end
        else begin
          buffer <= tmp;
          tmp <= data;
        end
    end

    wire [4:0] addr1 = {data != 0 && data != 'hF0 && buffer != 'hF0} ?  {1'd0,lut_out[3:0]} : 5'd16;
    wire [4:0] addr2 = {data != 0 && data != 'hF0 && buffer != 'hF0} ?  {1'd0,lut_out[7:4]} : 5'd16;
    rom u_rom1(
        .clk(clk),
        .rst_n(rst_n),
        .addr(addr1),
        .seg(seg1)
    );

    rom u_rom2(
        .clk(clk),
        .rst_n(rst_n),
        .addr(addr2),
        .seg(seg2)
    );
endmodule

example/fsm.v
module fsm (
    input        clk,
    input        rst_n,
    input  [7:0] data,
    input        en,
    output [2:0] state
);
    parameter IDLE = 3'b000;
    parameter ON   = 3'b001;
    parameter OFF  = 3'b010;
    parameter WAIT = 3'b100;

    reg [2:0] next_state;
    reg [2:0] current_state;

    always @(posedge clk or negedge rst_n) begin
      if(!rst_n)
        begin
          current_state <= IDLE;
        end
      else begin
          current_state <= next_state;
        end
    end

    always @(next_state or en) begin
        case(current_state)
            IDLE: if(data != 'h0F && en) next_state = ON;
                  else next_state = IDLE;

            ON: if(data == 'hF0) next_state = OFF;
                else next_state = ON;
                
            OFF: if(en)next_state = WAIT;
                 else next_state = OFF;

            WAIT:  next_state = IDLE;
            default : next_state = IDLE;
        endcase
    end
    assign state = current_state;
endmodule

PS/2/produce.v

module produce (
    input  [7:0] data,
    input  wire  clk,
    input        rst_n,
    input        en,
    output [7:0] counter1,
    output [7:0] counter2,
    output [7:0] ascii1,
    output [7:0] ascii2,
    output  [7:0] key1,
    output  [7:0] key2
);
    wire [2:0] state;
    reg  [7:0] counter;
    reg  [7:0] tmp;
    reg  [7:0] buffer;
    reg  [2:0] last_state;

    always @(posedge clk or negedge rst_n) begin
      if(!rst_n)
        begin
          last_state <= 0;
          counter <= 0;
          buffer <= 0;
          tmp <= 0;
        end
        else begin
          last_state <= state;
          buffer <= tmp;
          tmp <= data;
          if(last_state == 0 && state == 3'd1)
            counter <= counter + 8'd1;

        end
    end
    wire [4:0]addr1 = {data != 0 && data != 'hF0 && buffer != 'hF0} ?  {1'd0,data[3:0]} : 5'd16;
    wire [4:0]addr2 = {data != 0 && data != 'hF0 && buffer != 'hF0} ?  {1'd0,data[7:4]} : 5'd16;

    rom u_rom_counter1(.clk(clk),
              .rst_n(rst_n),
              .addr({1'b0,counter[7:4]}),
              .seg(counter1));
    rom u_rom_counter2(.clk(clk),
              .rst_n(rst_n),
              .addr({1'b0,counter[3:0]}),
              .seg(counter2));
    rom u_rom_ascii1(
      .clk(clk),
      .rst_n(rst_n),
      .addr(addr1),
      .seg(ascii1));
    rom u_rom_ascii2(
      .clk(clk),
      .rst_n(rst_n),
      .addr(addr2),
      .seg(ascii2));


    fsm u_fsm(
      .clk(clk),
      .rst_n(rst_n),
      .data(data),
      .en(en),
      .state(state)
    );
    
    rom_ascii u_ascii(
      .clk(clk),
      .rst_n(rst_n),
      .data(data),
      .seg1(key1),
      .seg2(key2)
    );


endmodule //produce

PS/2/keyboard.v
module keyboard (
    input        clk,
    input        rst_n, 
    input        ps2_data,
    input        ps2_clk,
    output [7:0] out,
    output   reg    en
);
    reg ready;
    reg [7:0] data;
    reg [9:0] buffer;
    reg [3:0] count;
    //detect falling/uping edge of ps2_clk
    reg [2:0] ps2_clk_sync;

    always @(posedge clk ) begin
        ps2_clk_sync <= {ps2_clk_sync[1:0],ps2_clk};
    end
    
    wire sampling = ps2_clk_sync[2] & ~ps2_clk_sync[1]; 

    
    always @(posedge clk ) begin
        if(!rst_n)begin
            buffer <= 0;
            count <= 0;
            en <= 0;
        end
        else begin
            if(sampling)begin
                if(count == 4'd10)begin
                    if((buffer[0] == 0) && ps2_data && ^buffer[9:1]) begin
                        data[7:0] <= buffer[8:1];
                        $display("receive %x", buffer[8:1]);
                        if(data != 'hf0)begin
                            en <= 1;
                        end
                        else en<=0;
                    end
                    count <= 0;
                end else begin
                    buffer[count] <= ps2_data;
                    count <= count + 3'b1;
                end
            end
        end
    end

    assign out = data;
endmodule //keyboard

PS/2/top.v
module top (
    input clk,
    input rst_n,
    input ps2_clk,
    input ps2_data,
    output [7:0] counter1,
    output [7:0] counter2,
    output [7:0] ascii1,
    output [7:0] ascii2,
    output  [7:0] key1,
    output  [7:0] key2
);
    wire[7:0] data;
    reg       en;

    keyboard u_keyboard(
        .clk(clk),
        .rst_n(rst_n),
        .ps2_data(ps2_data),
        .ps2_clk(ps2_clk),
        .out(data),
        .en(en)
    );

    produce u_produce(
        .clk(clk),
        .rst_n(rst_n),
        .en(en),
        .data(data),
        .counter1(counter1),
        .counter2(counter2),
        .ascii1(ascii1),
        .ascii2(ascii2),
        .key1(key1),
        .key2(key2)
    );
endmodule //main

PS/2/wave.vcd
$version Generated by VerilatedVcd $end
$date Wed Oct 11 06:14:44 2023 $end
$timescale 1s $end

 $scope module TOP $end
  $var wire  8 K! ascii1 [7:0] $end
  $var wire  8 L! ascii2 [7:0] $end
  $var wire  1 E! clk $end
  $var wire  8 I! counter1 [7:0] $end
  $var wire  8 J! counter2 [7:0] $end
  $var wire  8 M! key1 [7:0] $end
  $var wire  8 N! key2 [7:0] $end
  $var wire  1 G! ps2_clk $end
  $var wire  1 H! ps2_data $end
  $var wire  1 F! rst_n $end
  $scope module top $end
   $var wire  8 K! ascii1 [7:0] $end
   $var wire  8 L! ascii2 [7:0] $end
   $var wire  1 E! clk $end
   $var wire  8 I! counter1 [7:0] $end
   $var wire  8 J! counter2 [7:0] $end
   $var wire  8 :! data [7:0] $end
   $var wire  1 ;! en $end
   $var wire  8 M! key1 [7:0] $end
   $var wire  8 N! key2 [7:0] $end
   $var wire  1 G! ps2_clk $end
   $var wire  1 H! ps2_data $end
   $var wire  1 F! rst_n $end
   $scope module u_keyboard $end
    $var wire 10 <! buffer [9:0] $end
    $var wire  1 E! clk $end
    $var wire  4 =! count [3:0] $end
    $var wire  8 :! data [7:0] $end
    $var wire  1 ;! en $end
    $var wire  8 :! out [7:0] $end
    $var wire  1 G! ps2_clk $end
    $var wire  3 >! ps2_clk_sync [2:0] $end
    $var wire  1 H! ps2_data $end
    $var wire  1 P! ready $end
    $var wire  1 F! rst_n $end
    $var wire  1 ?! sampling $end
   $upscope $end
   $scope module u_produce $end
    $var wire  5 A! addr1 [4:0] $end
    $var wire  5 B! addr2 [4:0] $end
    $var wire  8 K! ascii1 [7:0] $end
    $var wire  8 L! ascii2 [7:0] $end
    $var wire  8 5! buffer [7:0] $end
    $var wire  1 E! clk $end
    $var wire  8 3! counter [7:0] $end
    $var wire  8 I! counter1 [7:0] $end
    $var wire  8 J! counter2 [7:0] $end
    $var wire  8 :! data [7:0] $end
    $var wire  1 ;! en $end
    $var wire  8 M! key1 [7:0] $end
    $var wire  8 N! key2 [7:0] $end
    $var wire  3 6! last_state [2:0] $end
    $var wire  1 F! rst_n $end
    $var wire  3 2! state [2:0] $end
    $var wire  8 4! tmp [7:0] $end
    $scope module u_ascii $end
     $var wire  8 U! addr [7:0] $end
     $var wire  5 C! addr1 [4:0] $end
     $var wire  5 D! addr2 [4:0] $end
     $var wire  8 9! buffer [7:0] $end
     $var wire  1 E! clk $end
     $var wire  8 :! data [7:0] $end
     $var wire 32 k i [31:0] $end
     $var wire  8 @! lut_out [7:0] $end
     $var wire  1 F! rst_n $end
     $var wire  8 M! seg1 [7:0] $end
     $var wire  8 N! seg2 [7:0] $end
     $var wire  8 4! tmp [7:0] $end
     $scope module u_rom1 $end
      $var wire  5 C! addr [4:0] $end
      $var wire  1 E! clk $end
      $var wire 32 } i [31:0] $end
      $var wire  8 l rom(0) [7:0] $end
      $var wire  8 m rom(1) [7:0] $end
      $var wire  8 v rom(10) [7:0] $end
      $var wire  8 w rom(11) [7:0] $end
      $var wire  8 x rom(12) [7:0] $end
      $var wire  8 y rom(13) [7:0] $end
      $var wire  8 z rom(14) [7:0] $end
      $var wire  8 { rom(15) [7:0] $end
      $var wire  8 | rom(16) [7:0] $end
      $var wire  8 n rom(2) [7:0] $end
      $var wire  8 o rom(3) [7:0] $end
      $var wire  8 p rom(4) [7:0] $end
      $var wire  8 q rom(5) [7:0] $end
      $var wire  8 r rom(6) [7:0] $end
      $var wire  8 s rom(7) [7:0] $end
      $var wire  8 t rom(8) [7:0] $end
      $var wire  8 u rom(9) [7:0] $end
      $var wire  1 F! rst_n $end
      $var wire  8 M! seg [7:0] $end
     $upscope $end
     $scope module u_rom2 $end
      $var wire  5 D! addr [4:0] $end
      $var wire  1 E! clk $end
      $var wire 32 1! i [31:0] $end
      $var wire  8 ~ rom(0) [7:0] $end
      $var wire  8 !! rom(1) [7:0] $end
      $var wire  8 *! rom(10) [7:0] $end
      $var wire  8 +! rom(11) [7:0] $end
      $var wire  8 ,! rom(12) [7:0] $end
      $var wire  8 -! rom(13) [7:0] $end
      $var wire  8 .! rom(14) [7:0] $end
      $var wire  8 /! rom(15) [7:0] $end
      $var wire  8 0! rom(16) [7:0] $end
      $var wire  8 "! rom(2) [7:0] $end
      $var wire  8 #! rom(3) [7:0] $end
      $var wire  8 $! rom(4) [7:0] $end
      $var wire  8 %! rom(5) [7:0] $end
      $var wire  8 &! rom(6) [7:0] $end
      $var wire  8 '! rom(7) [7:0] $end
      $var wire  8 (! rom(8) [7:0] $end
      $var wire  8 )! rom(9) [7:0] $end
      $var wire  1 F! rst_n $end
      $var wire  8 N! seg [7:0] $end
     $upscope $end
    $upscope $end
    $scope module u_fsm $end
     $var wire  3 Q! IDLE [2:0] $end
     $var wire  3 S! OFF [2:0] $end
     $var wire  3 R! ON [2:0] $end
     $var wire  3 T! WAIT [2:0] $end
     $var wire  1 E! clk $end
     $var wire  3 2! current_state [2:0] $end
     $var wire  8 :! data [7:0] $end
     $var wire  1 ;! en $end
     $var wire  3 O! next_state [2:0] $end
     $var wire  1 F! rst_n $end
     $var wire  3 2! state [2:0] $end
    $upscope $end
    $scope module u_rom_ascii1 $end
     $var wire  5 A! addr [4:0] $end
     $var wire  1 E! clk $end
     $var wire 32 X i [31:0] $end
     $var wire  8 G rom(0) [7:0] $end
     $var wire  8 H rom(1) [7:0] $end
     $var wire  8 Q rom(10) [7:0] $end
     $var wire  8 R rom(11) [7:0] $end
     $var wire  8 S rom(12) [7:0] $end
     $var wire  8 T rom(13) [7:0] $end
     $var wire  8 U rom(14) [7:0] $end
     $var wire  8 V rom(15) [7:0] $end
     $var wire  8 W rom(16) [7:0] $end
     $var wire  8 I rom(2) [7:0] $end
     $var wire  8 J rom(3) [7:0] $end
     $var wire  8 K rom(4) [7:0] $end
     $var wire  8 L rom(5) [7:0] $end
     $var wire  8 M rom(6) [7:0] $end
     $var wire  8 N rom(7) [7:0] $end
     $var wire  8 O rom(8) [7:0] $end
     $var wire  8 P rom(9) [7:0] $end
     $var wire  1 F! rst_n $end
     $var wire  8 K! seg [7:0] $end
    $upscope $end
    $scope module u_rom_ascii2 $end
     $var wire  5 B! addr [4:0] $end
     $var wire  1 E! clk $end
     $var wire 32 j i [31:0] $end
     $var wire  8 Y rom(0) [7:0] $end
     $var wire  8 Z rom(1) [7:0] $end
     $var wire  8 c rom(10) [7:0] $end
     $var wire  8 d rom(11) [7:0] $end
     $var wire  8 e rom(12) [7:0] $end
     $var wire  8 f rom(13) [7:0] $end
     $var wire  8 g rom(14) [7:0] $end
     $var wire  8 h rom(15) [7:0] $end
     $var wire  8 i rom(16) [7:0] $end
     $var wire  8 [ rom(2) [7:0] $end
     $var wire  8 \ rom(3) [7:0] $end
     $var wire  8 ] rom(4) [7:0] $end
     $var wire  8 ^ rom(5) [7:0] $end
     $var wire  8 _ rom(6) [7:0] $end
     $var wire  8 ` rom(7) [7:0] $end
     $var wire  8 a rom(8) [7:0] $end
     $var wire  8 b rom(9) [7:0] $end
     $var wire  1 F! rst_n $end
     $var wire  8 L! seg [7:0] $end
    $upscope $end
    $scope module u_rom_counter1 $end
     $var wire  5 7! addr [4:0] $end
     $var wire  1 E! clk $end
     $var wire 32 4 i [31:0] $end
     $var wire  8 # rom(0) [7:0] $end
     $var wire  8 $ rom(1) [7:0] $end
     $var wire  8 - rom(10) [7:0] $end
     $var wire  8 . rom(11) [7:0] $end
     $var wire  8 / rom(12) [7:0] $end
     $var wire  8 0 rom(13) [7:0] $end
     $var wire  8 1 rom(14) [7:0] $end
     $var wire  8 2 rom(15) [7:0] $end
     $var wire  8 3 rom(16) [7:0] $end
     $var wire  8 % rom(2) [7:0] $end
     $var wire  8 & rom(3) [7:0] $end
     $var wire  8 ' rom(4) [7:0] $end
     $var wire  8 ( rom(5) [7:0] $end
     $var wire  8 ) rom(6) [7:0] $end
     $var wire  8 * rom(7) [7:0] $end
     $var wire  8 + rom(8) [7:0] $end
     $var wire  8 , rom(9) [7:0] $end
     $var wire  1 F! rst_n $end
     $var wire  8 I! seg [7:0] $end
    $upscope $end
    $scope module u_rom_counter2 $end
     $var wire  5 8! addr [4:0] $end
     $var wire  1 E! clk $end
     $var wire 32 F i [31:0] $end
     $var wire  8 5 rom(0) [7:0] $end
     $var wire  8 6 rom(1) [7:0] $end
     $var wire  8 ? rom(10) [7:0] $end
     $var wire  8 @ rom(11) [7:0] $end
     $var wire  8 A rom(12) [7:0] $end
     $var wire  8 B rom(13) [7:0] $end
     $var wire  8 C rom(14) [7:0] $end
     $var wire  8 D rom(15) [7:0] $end
     $var wire  8 E rom(16) [7:0] $end
     $var wire  8 7 rom(2) [7:0] $end
     $var wire  8 8 rom(3) [7:0] $end
     $var wire  8 9 rom(4) [7:0] $end
     $var wire  8 : rom(5) [7:0] $end
     $var wire  8 ; rom(6) [7:0] $end
     $var wire  8 < rom(7) [7:0] $end
     $var wire  8 = rom(8) [7:0] $end
     $var wire  8 > rom(9) [7:0] $end
     $var wire  1 F! rst_n $end
     $var wire  8 J! seg [7:0] $end
    $upscope $end
   $upscope $end
  $upscope $end
 $upscope $end
$enddefinitions $end


#1
b00000000 #
b00000000 $
b00000000 %
b00000000 &
b00000000 '
b00000000 (
b00000000 )
b00000000 *
b00000000 +
b00000000 ,
b00000000 -
b00000000 .
b00000000 /
b00000000 0
b00000000 1
b00000000 2
b00000000 3
b00000000000000000000000000000000 4
b00000000 5
b00000000 6
b00000000 7
b00000000 8
b00000000 9
b00000000 :
b00000000 ;
b00000000 <
b00000000 =
b00000000 >
b00000000 ?
b00000000 @
b00000000 A
b00000000 B
b00000000 C
b00000000 D
b00000000 E
b00000000000000000000000000000000 F
b00000000 G
b00000000 H
b00000000 I
b00000000 J
b00000000 K
b00000000 L
b00000000 M
b00000000 N
b00000000 O
b00000000 P
b00000000 Q
b00000000 R
b00000000 S
b00000000 T
b00000000 U
b00000000 V
b00000000 W
b00000000000000000000000000000000 X
b00000000 Y
b00000000 Z
b00000000 [
b00000000 \
b00000000 ]
b00000000 ^
b00000000 _
b00000000 `
b00000000 a
b00000000 b
b00000000 c
b00000000 d
b00000000 e
b00000000 f
b00000000 g
b00000000 h
b00000000 i
b00000000000000000000000000000000 j
b00000000000000000000000000100100 k
b00000000 l
b00000000 m
b00000000 n
b00000000 o
b00000000 p
b00000000 q
b00000000 r
b00000000 s
b00000000 t
b00000000 u
b00000000 v
b00000000 w
b00000000 x
b00000000 y
b00000000 z
b00000000 {
b00000000 |
b00000000000000000000000000000000 }
b00000000 ~
b00000000 !!
b00000000 "!
b00000000 #!
b00000000 $!
b00000000 %!
b00000000 &!
b00000000 '!
b00000000 (!
b00000000 )!
b00000000 *!
b00000000 +!
b00000000 ,!
b00000000 -!
b00000000 .!
b00000000 /!
b00000000 0!
b00000000000000000000000000000000 1!
b000 2!
b00000000 3!
b00000000 4!
b00000000 5!
b000 6!
b00000 7!
b00000 8!
b00000000 9!
b00000000 :!
0;!
b0000000000 <!
b0000 =!
b000 >!
0?!
b00000000 @!
b10000 A!
b10000 B!
b10000 C!
b10000 D!
0E!
0F!
1G!
1H!
b00000000 I!
b00000000 J!
b00000000 K!
b00000000 L!
b00000000 M!
b00000000 N!
b000 O!
0P!
b000 Q!
b001 R!
b010 S!
b100 T!
b00000000 U!
#2
b11111100 #
b01100000 $
b11011010 %
b11110010 &
b01100110 '
b10110110 (
b10111110 )
b11100000 *
b11111110 +
b11110110 ,
b11101110 -
b11111110 .
b10011100 /
b11111100 0
b10011110 1
b10001110 2
b11111100 5
b01100000 6
b11011010 7
b11110010 8
b01100110 9
b10110110 :
b10111110 ;
b11100000 <
b11111110 =
b11110110 >
b11101110 ?
b11111110 @
b10011100 A
b11111100 B
b10011110 C
b10001110 D
b11111100 G
b01100000 H
b11011010 I
b11110010 J
b01100110 K
b10110110 L
b10111110 M
b11100000 N
b11111110 O
b11110110 P
b11101110 Q
b11111110 R
b10011100 S
b11111100 T
b10011110 U
b10001110 V
b11111100 Y
b01100000 Z
b11011010 [
b11110010 \
b01100110 ]
b10110110 ^
b10111110 _
b11100000 `
b11111110 a
b11110110 b
b11101110 c
b11111110 d
b10011100 e
b11111100 f
b10011110 g
b10001110 h
b11111100 l
b01100000 m
b11011010 n
b11110010 o
b01100110 p
b10110110 q
b10111110 r
b11100000 s
b11111110 t
b11110110 u
b11101110 v
b11111110 w
b10011100 x
b11111100 y
b10011110 z
b10001110 {
b11111100 ~
b01100000 !!
b11011010 "!
b11110010 #!
b01100110 $!
b10110110 %!
b10111110 &!
b11100000 '!
b11111110 (!
b11110110 )!
b11101110 *!
b11111110 +!
b10011100 ,!
b11111100 -!
b10011110 .!
b10001110 /!
b001 >!
1E!
#3
0E!
#4
b011 >!
1E!
#5
0E!
#6
b111 >!
1E!
#7
0E!
#8
1E!
#9
0E!
#10
b00000000000000000000000000010000 4
b00000000000000000000000000010000 F
b00000000000000000000000000010000 X
b00000000000000000000000000010000 j
b00000000000000000000000000010000 }
b00000000000000000000000000010000 1!
1E!
1F!
b11111100 I!
b11111100 J!
#11
0E!
0H!
#12
1E!
#13
0E!
#14
1E!
#15
0E!
#16
1E!
#17
0E!
#18
1E!
#19
0E!
#20
1E!
#21
0E!
0G!
#22
b110 >!
1E!
#23
0E!
#24
b100 >!
1?!
1E!
#25
0E!
#26
b0001 =!
b001 >!
0?!
1E!
1G!
#27
0E!
#28
b011 >!
1E!
#29
0E!
#30
b111 >!
1E!
#31
0E!
0G!
1H!
#32
b110 >!
1E!
#33
0E!
#34
b100 >!
1?!
1E!
#35
0E!
#36
b0000000010 <!
b0010 =!
b001 >!
0?!
1E!
1G!
#37
0E!
#38
b011 >!
1E!
#39
0E!
#40
b111 >!
1E!
#41
0E!
0G!
0H!
#42
b110 >!
1E!
#43
0E!
#44
b100 >!
1?!
1E!
#45
0E!
#46
b0011 =!
b001 >!
0?!
1E!
1G!
#47
0E!
#48
b011 >!
1E!
#49
0E!
#50
b111 >!
1E!
#51
0E!
0G!
1H!
#52
b110 >!
1E!
#53
0E!
#54
b100 >!
1?!
1E!
#55
0E!
#56
b0000001010 <!
b0100 =!
b001 >!
0?!
1E!
1G!
#57
0E!
#58
b011 >!
1E!
#59
0E!
#60
b111 >!
1E!
#61
0E!
0G!
#62
b110 >!
1E!
#63
0E!
#64
b100 >!
1?!
1E!
#65
0E!
#66
b0000011010 <!
b0101 =!
b001 >!
0?!
1E!
1G!
#67
0E!
#68
b011 >!
1E!
#69
0E!
#70
b111 >!
1E!
#71
0E!
0G!
#72
b110 >!
1E!
#73
0E!
#74
b100 >!
1?!
1E!
#75
0E!
#76
b0000111010 <!
b0110 =!
b001 >!
0?!
1E!
1G!
#77
0E!
#78
b011 >!
1E!
#79
0E!
#80
b111 >!
1E!
#81
0E!
0G!
0H!
#82
b110 >!
1E!
#83
0E!
#84
b100 >!
1?!
1E!
#85
0E!
#86
b0111 =!
b001 >!
0?!
1E!
1G!
#87
0E!
#88
b011 >!
1E!
#89
0E!
#90
b111 >!
1E!
#91
0E!
0G!
#92
b110 >!
1E!
#93
0E!
#94
b100 >!
1?!
1E!
#95
0E!
#96
b1000 =!
b001 >!
0?!
1E!
1G!
#97
0E!
#98
b011 >!
1E!
#99
0E!
#100
b111 >!
1E!
#101
0E!
0G!
#102
b110 >!
1E!
#103
0E!
#104
b100 >!
1?!
1E!
#105
0E!
#106
b1001 =!
b001 >!
0?!
1E!
1G!
#107
0E!
#108
b011 >!
1E!
#109
0E!
#110
b111 >!
1E!
#111
0E!
0G!
1H!
#112
b110 >!
1E!
#113
0E!
#114
b100 >!
1?!
1E!
#115
0E!
#116
b1000111010 <!
b1010 =!
b001 >!
0?!
1E!
1G!
#117
0E!
#118
b011 >!
1E!
#119
0E!
#120
b111 >!
1E!
#121
0E!
0G!
#122
b110 >!
1E!
#123
0E!
#124
b100 >!
1?!
1E!
#125
0E!
#126
b00011101 :!
1;!
b0000 =!
b001 >!
0?!
b01010111 @!
b01101 A!
b00001 B!
b00111 C!
b00101 D!
1E!
1G!
b11111100 K!
b01100000 L!
b11100000 M!
b10110110 N!
b001 O!
#127
0E!
#128
b001 2!
b00011101 4!
0;!
b0000000000 <!
b011 >!
1E!
#129
0E!
#130
b00000001 3!
b00011101 5!
b001 6!
b00001 8!
b00011101 9!
b111 >!
1E!
b01100000 J!
#131
0E!
0G!
#132
b110 >!
1E!
#133
0E!
#134
b100 >!
1?!
1E!
#135
0E!
#136
b0000000001 <!
b0001 =!
b001 >!
0?!
1E!
1G!
#137
0E!
#138
b011 >!
1E!
#139
0E!
#140
b111 >!
1E!
#141
0E!
0G!
#142
b110 >!
1E!
#143
0E!
#144
b100 >!
1?!
1E!
#145
0E!
#146
b0000000011 <!
b0010 =!
b001 >!
0?!
1E!
1G!
#147
0E!
#148
b011 >!
1E!
#149
0E!
#150
b111 >!
1E!
#151
0E!
0G!
#152
b110 >!
1E!
#153
0E!
#154
b100 >!
1?!
1E!
#155
0E!
#156
b0000000111 <!
b0011 =!
b001 >!
0?!
1E!
1G!
#157
0E!
#158
b011 >!
1E!
#159
0E!
#160
b111 >!
1E!
#161
0E!
0G!
#162
b110 >!
1E!
#163
0E!
#164
b100 >!
1?!
1E!
#165
0E!
#166
b0000001111 <!
b0100 =!
b001 >!
0?!
1E!
1G!
#167
0E!
#168
b011 >!
1E!
#169
0E!
#170
b111 >!
1E!
#171
0E!
0G!
#172
b110 >!
1E!
#173
0E!
#174
b100 >!
1?!
1E!
#175
0E!
#176
b0000011111 <!
b0101 =!
b001 >!
0?!
1E!
1G!
#177
0E!
#178
b011 >!
1E!
#179
0E!
#180
b111 >!
1E!
#181
0E!
0G!
#182
b110 >!
1E!
#183
0E!
#184
b100 >!
1?!
1E!
#185
0E!
#186
b0000111111 <!
b0110 =!
b001 >!
0?!
1E!
1G!
#187
0E!
#188
b011 >!
1E!
#189
0E!
#190
b111 >!
1E!
#191
0E!
0G!
#192
b110 >!
1E!
#193
0E!
#194
b100 >!
1?!
1E!
#195
0E!
#196
b0001111111 <!
b0111 =!
b001 >!
0?!
1E!
1G!
#197
0E!
#198
b011 >!
1E!
#199
0E!
#200
b111 >!
1E!
