mux/mux.v

module mux (
    input [1:0] A,
    input [1:0] B,
    input [1:0] C,
    input [1:0] D,
    input [1:0] Y,
    output reg [1:0] out
);
    wire [15:0] lut = { 2'b00, {A},
                        2'b01, {B},
                        2'b10, {C},
                        2'b11, {D}};
    wire [3:0] pair_list [3:0];
    wire [1:0] key_list [3:0];
    wire [1:0] data_list [3:0];
    
    generate
        for(genvar n = 0;n < 4;n = n + 1)begin
            assign pair_list[n] = lut[4*(n+1)-1:4*n];
            assign data_list[n] = pair_list[n][1:0];
            assign key_list[n] = pair_list[n][3:2];
        end
    endgenerate
    
    reg [1:0] lut_out;
    integer i;

    always @(*)begin
        lut_out = 0;
        for (i = 0; i < 4 ;i = i + 1) begin
            lut_out = lut_out | ({2{Y == key_list[i]}} & data_list[i]);
        end
        out[1:0] = lut_out[1:0];
    end

endmodule

mux/wave.vcd
$version Generated by VerilatedVcd $end
$date Wed Oct  4 20:24:58 2023 $end
$timescale 1s $end

 $scope module TOP $end
  $var wire  2 1 A [1:0] $end
  $var wire  2 2 B [1:0] $end
  $var wire  2 3 C [1:0] $end
  $var wire  2 4 D [1:0] $end
  $var wire  2 5 Y [1:0] $end
  $var wire  2 6 out [1:0] $end
  $scope module mux $end
   $var wire  2 1 A [1:0] $end
   $var wire  2 2 B [1:0] $end
   $var wire  2 3 C [1:0] $end
   $var wire  2 4 D [1:0] $end
   $var wire  2 5 Y [1:0] $end
   $var wire  2 , data_list(0) [1:0] $end
   $var wire  2 - data_list(1) [1:0] $end
   $var wire  2 . data_list(2) [1:0] $end
   $var wire  2 / data_list(3) [1:0] $end
   $var wire 32 7 i [31:0] $end
   $var wire  2 ( key_list(0) [1:0] $end
   $var wire  2 ) key_list(1) [1:0] $end
   $var wire  2 * key_list(2) [1:0] $end
   $var wire  2 + key_list(3) [1:0] $end
   $var wire 16 # lut [15:0] $end
   $var wire  2 0 lut_out [1:0] $end
   $var wire  2 6 out [1:0] $end
   $var wire  4 $ pair_list(0) [3:0] $end
   $var wire  4 % pair_list(1) [3:0] $end
   $var wire  4 & pair_list(2) [3:0] $end
   $var wire  4 ' pair_list(3) [3:0] $end
  $upscope $end
 $upscope $end
$enddefinitions $end


#1
b0000010010001100 #
b1100 $
b1000 %
b0100 &
b0000 '
b11 (
b10 )
b01 *
b00 +
b00 ,
b00 -
b00 .
b00 /
b00 0
b00 1
b00 2
b00 3
b00 4
b00 5
b00 6
b00000000000000000000000000000100 7
#2
b0000010010001101 #
b1101 $
b01 ,
b01 4
#3
b0000010010001110 #
b1110 $
b10 ,
b10 4
#4
b0000010010001111 #
b1111 $
b11 ,
b11 4
#5
b0000010010011100 #
b1100 $
b1001 %
b00 ,
b01 -
b01 3
b00 4
#6
b0000010010011101 #
b1101 $
b01 ,
b01 4
#7
b0000010010011110 #
b1110 $
b10 ,
b10 4
#8
b0000010010011111 #
b1111 $
b11 ,
b11 4
#9
b0000010010101100 #
b1100 $
b1010 %
b00 ,
b10 -
b10 3
b00 4
#10
b0000010010101101 #
b1101 $
b01 ,
b01 4
#11
b0000010010101110 #
b1110 $
b10 ,
b10 4
#12
b0000010010101111 #
b1111 $
b11 ,
b11 4
#13
b0000010010111100 #
b1100 $
b1011 %
b00 ,
b11 -
b11 3
b00 4
#14
b0000010010111101 #
b1101 $
b01 ,
b01 4
#15
b0000010010111110 #
b1110 $
b10 ,
b10 4
#16
b0000010010111111 #
b1111 $
b11 ,
b11 4
#17
b0000010110001100 #
b1100 $
b1000 %
b0101 &
b00 ,
b00 -
b01 .
b01 2
b00 3
b00 4
#18
b0000010110001101 #
b1101 $
b01 ,
b01 4
#19
b0000010110001110 #
b1110 $
b10 ,
b10 4
#20
b0000010110001111 #
b1111 $
b11 ,
b11 4
#21
b0000010110011100 #
b1100 $
b1001 %
b00 ,
b01 -
b01 3
b00 4
#22
b0000010110011101 #
b1101 $
b01 ,
b01 4
#23
b0000010110011110 #
b1110 $
b10 ,
b10 4
#24
b0000010110011111 #
b1111 $
b11 ,
b11 4
#25
b0000010110101100 #
b1100 $
b1010 %
b00 ,
b10 -
b10 3
b00 4
#26
b0000010110101101 #
b1101 $
b01 ,
b01 4
#27
b0000010110101110 #
b1110 $
b10 ,
b10 4
#28
b0000010110101111 #
b1111 $
b11 ,
b11 4
#29
b0000010110111100 #
b1100 $
b1011 %
b00 ,
b11 -
b11 3
b00 4
#30
b0000010110111101 #
b1101 $
b01 ,
b01 4
#31
b0000010110111110 #
b1110 $
b10 ,
b10 4
#32
b0000010110111111 #
b1111 $
b11 ,
b11 4
#33
b0000011010001100 #
b1100 $
b1000 %
b0110 &
b00 ,
b00 -
b10 .
b10 2
b00 3
b00 4
#34
b0000011010001101 #
b1101 $
b01 ,
b01 4
#35
b0000011010001110 #
b1110 $
b10 ,
b10 4
#36
b0000011010001111 #
b1111 $
b11 ,
b11 4
#37
b0000011010011100 #
b1100 $
b1001 %
b00 ,
b01 -
b01 3
b00 4
#38
b0000011010011101 #
b1101 $
b01 ,
b01 4
#39
b0000011010011110 #
b1110 $
b10 ,
b10 4
#40
b0000011010011111 #
b1111 $
b11 ,
b11 4
#41
b0000011010101100 #
b1100 $
b1010 %
b00 ,
b10 -
b10 3
b00 4
#42
b0000011010101101 #
b1101 $
b01 ,
b01 4
#43
b0000011010101110 #
b1110 $
b10 ,
b10 4
#44
b0000011010101111 #
b1111 $
b11 ,
b11 4
#45
b0000011010111100 #
b1100 $
b1011 %
b00 ,
b11 -
b11 3
b00 4
#46
b0000011010111101 #
b1101 $
b01 ,
b01 4
#47
b0000011010111110 #
b1110 $
b10 ,
b10 4
#48
b0000011010111111 #
b1111 $
b11 ,
b11 4
#49
b0000011110001100 #
b1100 $
b1000 %
b0111 &
b00 ,
b00 -
b11 .
b11 2
b00 3
b00 4
#50
b0000011110001101 #
b1101 $
b01 ,
b01 4
#51
b0000011110001110 #
b1110 $
b10 ,
b10 4
#52
b0000011110001111 #
b1111 $
b11 ,
b11 4
#53
b0000011110011100 #
b1100 $
b1001 %
b00 ,
b01 -
b01 3
b00 4
#54
b0000011110011101 #
b1101 $
b01 ,
b01 4
#55
b0000011110011110 #
b1110 $
b10 ,
b10 4
#56
b0000011110011111 #
b1111 $
b11 ,
b11 4
#57
b0000011110101100 #
b1100 $
b1010 %
b00 ,
b10 -
b10 3
b00 4
#58
b0000011110101101 #
b1101 $
b01 ,
b01 4
#59
b0000011110101110 #
b1110 $
b10 ,
b10 4
#60
b0000011110101111 #
b1111 $
b11 ,
b11 4
#61
b0000011110111100 #
b1100 $
b1011 %
b00 ,
b11 -
b11 3
b00 4
#62
b0000011110111101 #
b1101 $
b01 ,
b01 4
#63
b0000011110111110 #
b1110 $
b10 ,
b10 4
#64
b0000011110111111 #
b1111 $
b11 ,
b11 4
#65
b0001010010001100 #
b1100 $
b1000 %
b0100 &
b0001 '
b00 ,
b00 -
b00 .
b01 /
b01 0
b01 1
b00 2
b00 3
b00 4
b01 6
#66
b0001010010001101 #
b1101 $
b01 ,
b01 4
#67
b0001010010001110 #
b1110 $
b10 ,
b10 4
#68
b0001010010001111 #
b1111 $
b11 ,
b11 4
#69
b0001010010011100 #
b1100 $
b1001 %
b00 ,
b01 -
b01 3
b00 4
#70
b0001010010011101 #
b1101 $
b01 ,
b01 4
#71
b0001010010011110 #
b1110 $
b10 ,
b10 4
#72
b0001010010011111 #
b1111 $
b11 ,
b11 4
#73
b0001010010101100 #
b1100 $
b1010 %
b00 ,
b10 -
b10 3
b00 4
#74
b0001010010101101 #
b1101 $
b01 ,
b01 4
#75
b0001010010101110 #
b1110 $
b10 ,
b10 4
#76
b0001010010101111 #
b1111 $
b11 ,
b11 4
#77
b0001010010111100 #
b1100 $
b1011 %
b00 ,
b11 -
b11 3
b00 4
#78
b0001010010111101 #
b1101 $
b01 ,
b01 4
#79
b0001010010111110 #
b1110 $
b10 ,
b10 4
#80
b0001010010111111 #
b1111 $
b11 ,
b11 4
#81
b0001010110001100 #
b1100 $
b1000 %
b0101 &
b00 ,
b00 -
b01 .
b01 2
b00 3
b00 4
#82
b0001010110001101 #
b1101 $
b01 ,
b01 4
#83
b0001010110001110 #
b1110 $
b10 ,
b10 4
#84
b0001010110001111 #
b1111 $
b11 ,
b11 4
#85
b0001010110011100 #
b1100 $
b1001 %
b00 ,
b01 -
b01 3
b00 4
#86
b0001010110011101 #
b1101 $
b01 ,
b01 4
#87
b0001010110011110 #
b1110 $
b10 ,
b10 4
#88
b0001010110011111 #
b1111 $
b11 ,
b11 4
#89
b0001010110101100 #
b1100 $
b1010 %
b00 ,
b10 -
b10 3
b00 4
#90
b0001010110101101 #
b1101 $
b01 ,
b01 4
#91
b0001010110101110 #
b1110 $
b10 ,
b10 4
#92
b0001010110101111 #
b1111 $
b11 ,
b11 4
#93
b0001010110111100 #
b1100 $
b1011 %
b00 ,
b11 -
b11 3
b00 4
#94
b0001010110111101 #
b1101 $
b01 ,
b01 4
#95
b0001010110111110 #
b1110 $
b10 ,
b10 4
#96
b0001010110111111 #
b1111 $
b11 ,
b11 4
#97
b0001011010001100 #
b1100 $
b1000 %
b0110 &
b00 ,
b00 -
b10 .
b10 2
b00 3
b00 4
#98
b0001011010001101 #
b1101 $
b01 ,
b01 4
#99
b0001011010001110 #
b1110 $
b10 ,
b10 4
#100
b0001011010001111 #
b1111 $
b11 ,
b11 4
#101
b0001011010011100 #
b1100 $
b1001 %
b00 ,
b01 -
b01 3
b00 4
#102
b0001011010011101 #
b1101 $
b01 ,
b01 4
#103
b0001011010011110 #
b1110 $
b10 ,
b10 4
#104
b0001011010011111 #
b1111 $
b11 ,
b11 4
#105
b0001011010101100 #
b1100 $
b1010 %
b00 ,
b10 -
b10 3
b00 4
#106
b0001011010101101 #
b1101 $
b01 ,
b01 4
#107
b0001011010101110 #
b1110 $
b10 ,
b10 4
#108
b0001011010101111 #
b1111 $
b11 ,
b11 4
#109
b0001011010111100 #
b1100 $
b1011 %
b00 ,
b11 -
b11 3
b00 4
#110
b0001011010111101 #
b1101 $
b01 ,
b01 4
#111
b0001011010111110 #
b1110 $
b10 ,
b10 4
#112
b0001011010111111 #
b1111 $
b11 ,
b11 4
#113
b0001011110001100 #
b1100 $
b1000 %
b0111 &
b00 ,
b00 -
b11 .
b11 2
b00 3
b00 4
#114
b0001011110001101 #
b1101 $
b01 ,
b01 4
#115
b0001011110001110 #
b1110 $
b10 ,
b10 4
#116
b0001011110001111 #
b1111 $
b11 ,
b11 4
#117
b0001011110011100 #
b1100 $
b1001 %
b00 ,
b01 -
b01 3
b00 4
#118
b0001011110011101 #
b1101 $
b01 ,
b01 4
#119
b0001011110011110 #
b1110 $
b10 ,
b10 4
#120
b0001011110011111 #
b1111 $
b11 ,
b11 4
#121
b0001011110101100 #
b1100 $
b1010 %
b00 ,
b10 -
b10 3
b00 4
#122
b0001011110101101 #
b1101 $
b01 ,
b01 4
#123
b0001011110101110 #
b1110 $
b10 ,
b10 4
#124
b0001011110101111 #
b1111 $
b11 ,
b11 4
#125
b0001011110111100 #
b1100 $
b1011 %
b00 ,
b11 -
b11 3
b00 4
#126
b0001011110111101 #
b1101 $
b01 ,
b01 4
#127
b0001011110111110 #
b1110 $
b10 ,
b10 4
#128
b0001011110111111 #
b1111 $
b11 ,
b11 4
#129
b0010010010001100 #
b1100 $
b1000 %
b0100 &
b0010 '
b00 ,
b00 -
b00 .
b10 /
b10 0
b10 1
b00 2
b00 3
b00 4
b10 6
#130
b0010010010001101 #
b1101 $
b01 ,
b01 4
#131
b0010010010001110 #
b1110 $
b10 ,
b10 4
#132
b0010010010001111 #
b1111 $
b11 ,
b11 4
#133
b0010010010011100 #
b1100 $
b1001 %
b00 ,
b01 -
b01 3
b00 4
#134
b0010010010011101 #
b1101 $
b01 ,
b01 4
#135
b0010010010011110 #
b1110 $
b10 ,
b10 4
#136
b0010010010011111 #
b1111 $
b11 ,
b11 4
#137
b0010010010101100 #
b1100 $
b1010 %
b00 ,
b10 -
b10 3
b00 4
#138
b0010010010101101 #
b1101 $
b01 ,
b01 4
#139
b0010010010101110 #
b1110 $
b10 ,
b10 4
#140
b0010010010101111 #
b1111 $
b11 ,
b11 4
#141
b0010010010111100 #
b1100 $
b1011 %
b00 ,
b11 -
b11 3
b00 4
#142
b0010010010111101 #
b1101 $
b01 ,
b01 4
#143
b0010010010111110 #
b1110 $
b10 ,
b10 4
#144
b0010010010111111 #
b1111 $
b11 ,
b11 4
#145
b0010010110001100 #
b1100 $
b1000 %
b0101 &
b00 ,
b00 -
b01 .
b01 2
b00 3
b00 4
#146
b0010010110001101 #
b1101 $
b01 ,
b01 4
#147
b0010010110001110 #
b1110 $
b10 ,
b10 4
#148
b0010010110001111 #
b1111 $
b11 ,
b11 4
#149
b0010010110011100 #
b1100 $
b1001 %
b00 ,
b01 -
b01 3
b00 4
#150
b0010010110011101 #
b1101 $
b01 ,
b01 4
#151
b0010010110011110 #
b1110 $
b10 ,
b10 4
#152
b0010010110011111 #
b1111 $
b11 ,
b11 4
#153
b0010010110101100 #
b1100 $
b1010 %
b00 ,
b10 -
b10 3
b00 4
#154
b0010010110101101 #
b1101 $
b01 ,
b01 4
#155
b0010010110101110 #
b1110 $
b10 ,
b10 4
#156
b0010010110101111 #
b1111 $
b11 ,
b11 4
#157
b0010010110111100 #
b1100 $
b1011 %
b00 ,
b11 -
b11 3
b00 4
#158
b0010010110111101 #
b1101 $
b01 ,
b01 4
#159
b0010010110111110 #
b1110 $
b10 ,
b10 4
#160
b0010010110111111 #
b1111 $
b11 ,
b11 4
#161
b0010011010001100 #
b1100 $
b1000 %
b0110 &
b00 ,
b00 -
b10 .
b10 2
b00 3
b00 4
#162
b0010011010001101 #
b1101 $
b01 ,
b01 4
#163
b0010011010001110 #
b1110 $
b10 ,
b10 4
#164
b0010011010001111 #
b1111 $
b11 ,
b11 4
#165
b0010011010011100 #
b1100 $
b1001 %
b00 ,
b01 -
b01 3
b00 4
#166
b0010011010011101 #
b1101 $
b01 ,
b01 4
#167
b0010011010011110 #
b1110 $
b10 ,
b10 4
#168
b0010011010011111 #
b1111 $
b11 ,
b11 4
#169
b0010011010101100 #
b1100 $
b1010 %
b00 ,
b10 -
b10 3
b00 4
#170
b0010011010101101 #
b1101 $
b01 ,
b01 4
#171
b0010011010101110 #
b1110 $
b10 ,
b10 4
#172
b0010011010101111 #
b1111 $
b11 ,
b11 4
#173
b0010011010111100 #
b1100 $
b1011 %
b00 ,
b11 -
b11 3
b00 4
#174
b0010011010111101 #
b1101 $
b01 ,
b01 4
#175
b0010011010111110 #
b1110 $
b10 ,
b10 4
#176
b0010011010111111 #
b1111 $
b11 ,
b11 4
#177
b0010011110001100 #
b1100 $
b1000 %
b0111 &
b00 ,
b00 -
b11 .
b11 2
b00 3
b00 4
#178
b0010011110001101 #
b1101 $
b01 ,
b01 4
#179
b0010011110001110 #
b1110 $
b10 ,
b10 4
#180
b0010011110001111 #
b1111 $
b11 ,
b11 4
#181
b0010011110011100 #
b1100 $
b1001 %
b00 ,
b01 -
b01 3
b00 4
#182
b0010011110011101 #
b1101 $
b01 ,
b01 4
#183
b0010011110011110 #
b1110 $
b10 ,
b10 4
#184
b0010011110011111 #
b1111 $
b11 ,
b11 4
#185
b0010011110101100 #
b1100 $
b1010 %
b00 ,
b10 -
b10 3
b00 4
#186
b0010011110101101 #
b1101 $
b01 ,
b01 4
#187
b0010011110101110 #
b1110 $
b10 ,
b10 4
#188
b0010011110101111 #
b1111 $
b11 ,
b11 4
#189
b0010011110111100 #
b1100 $
b1011 %
b00 ,
b11 -
b11 3
b00 4
#190
b0010011110111101 #
b1101 $
b01 ,
b01 4
#191
b0010011110111110 #
b1110 $
b10 ,
b10 4
#192
b0010011110111111 #
b1111 $
b11 ,
b11 4
#193
b0011010010001100 #
b1100 $
b1000 %
b0100 &
b0011 '
b00 ,
b00 -
b00 .
b11 /
b11 0
b11 1
b00 2
b00 3
b00 4
b11 6
#194
b0011010010001101 #
b1101 $
b01 ,
b01 4
#195
b0011010010001110 #
b1110 $
b10 ,
b10 4
#196
b0011010010001111 #
b1111 $
b11 ,
b11 4
#197
b0011010010011100 #
b1100 $
b1001 %
b00 ,
b01 -
b01 3
b00 4
#198
b0011010010011101 #
b1101 $
b01 ,
b01 4
#199
b0011010010011110 #
b1110 $
b10 ,
b10 4
#200
b0011010010011111 #
b1111 $
b11 ,
b11 4
#201
b0011010010101100 #
b1100 $
b1010 %
b00 ,
b10 -
b10 3
b00 4
#202
b0011010010101101 #
b1101 $
b01 ,
b01 4
#203
b0011010010101110 #
b1110 $
b10 ,
b10 4
#204
b0011010010101111 #
b1111 $
b11 ,
b11 4
#205
b0011010010111100 #
b1100 $
b1011 %
b00 ,
b11 -
b11 3
b00 4
#206
b0011010010111101 #
b1101 $
b01 ,
b01 4
#207
b0011010010111110 #
b1110 $
b10 ,
b10 4
#208
b0011010010111111 #
b1111 $
b11 ,
b11 4
#209
b0011010110001100 #
b1100 $
b1000 %
b0101 &
b00 ,
b00 -
b01 .
b01 2
b00 3
b00 4
#210
b0011010110001101 #
b1101 $
b01 ,
b01 4
#211
b0011010110001110 #
b1110 $
b10 ,
b10 4
#212
b0011010110001111 #
b1111 $
b11 ,
b11 4
#213
b0011010110011100 #
b1100 $
b1001 %
b00 ,
b01 -
b01 3
b00 4
#214
b0011010110011101 #
b1101 $
b01 ,
b01 4
#215
b0011010110011110 #
b1110 $
b10 ,
b10 4
#216
b0011010110011111 #
b1111 $
b11 ,
b11 4
#217
b0011010110101100 #
b1100 $
b1010 %
b00 ,
b10 -
b10 3
b00 4
#218
b0011010110101101 #
b1101 $
b01 ,
b01 4
#219
b0011010110101110 #
b1110 $
b10 ,
b10 4
#220
b0011010110101111 #
b1111 $
b11 ,
b11 4
#221
b0011010110111100 #
b1100 $
b1011 %
b00 ,
b11 -
b11 3
b00 4
#222
b0011010110111101 #
b1101 $
b01 ,
b01 4
#223
b0011010110111110 #
b1110 $
b10 ,
b10 4
#224
b0011010110111111 #
b1111 $
b11 ,
b11 4
#225
b0011011010001100 #
b1100 $
b1000 %
b0110 &
b00 ,
b00 -
b10 .
b10 2
b00 3
b00 4
#226
b0011011010001101 #
b1101 $
b01 ,
b01 4
#227
b0011011010001110 #
b1110 $
b10 ,
b10 4
#228
b0011011010001111 #
b1111 $
b11 ,
b11 4
#229
b0011011010011100 #
b1100 $
b1001 %
b00 ,
b01 -
b01 3
b00 4
#230
b0011011010011101 #
b1101 $
b01 ,
b01 4
#231
b0011011010011110 #
b1110 $
b10 ,
b10 4
#232
b0011011010011111 #
b1111 $
b11 ,
b11 4
#233
b0011011010101100 #
b1100 $
b1010 %
b00 ,
b10 -
b10 3
b00 4
#234
b0011011010101101 #
b1101 $
b01 ,
b01 4
#235
b0011011010101110 #
b1110 $
b10 ,
b10 4
#236
b0011011010101111 #
b1111 $
b11 ,
b11 4
#237
b0011011010111100 #
b1100 $
b1011 %
b00 ,
b11 -
b11 3
b00 4
#238
b0011011010111101 #
b1101 $
b01 ,
b01 4
#239
b0011011010111110 #
b1110 $
b10 ,
b10 4
#240
b0011011010111111 #
b1111 $
b11 ,
b11 4
#241
b0011011110001100 #
b1100 $
b1000 %
b0111 &
b00 ,
b00 -
b11 .
b11 2
b00 3
b00 4
#242
b0011011110001101 #
b1101 $
b01 ,
b01 4
#243
b0011011110001110 #
b1110 $
b10 ,
b10 4
#244
b0011011110001111 #
b1111 $
b11 ,
b11 4
#245
b0011011110011100 #
b1100 $
b1001 %
b00 ,
b01 -
b01 3
b00 4
#246
b0011011110011101 #
b1101 $
b01 ,
b01 4
#247
b0011011110011110 #
b1110 $
b10 ,
b10 4
#248
b0011011110011111 #
b1111 $
b11 ,
b11 4
#249
b0011011110101100 #
b1100 $
b1010 %
b00 ,
b10 -
b10 3
b00 4
#250
b0011011110101101 #
b1101 $
b01 ,
b01 4
#251
b0011011110101110 #
b1110 $
b10 ,
b10 4
#252
b0011011110101111 #
b1111 $
b11 ,
b11 4
#253
b0011011110111100 #
b1100 $
b1011 %
b00 ,
b11 -
b11 3
b00 4
#254
b0011011110111101 #
b1101 $
b01 ,
b01 4
#255
b0011011110111110 #
b1110 $
b10 ,
b10 4
#256
b0011011110111111 #
b1111 $
b11 ,
b11 4
#257
b0000010010001100 #
b1100 $
b1000 %
b0100 &
b0000 '
b00 ,
b00 -
b00 .
b00 /
b00 0
b00 1
b00 2
b00 3
b00 4
b10 5
b00 6
#258
b0000010010001101 #
b1101 $
b01 ,
b01 4
#259
b0000010010001110 #
b1110 $
b10 ,
b10 4
#260
b0000010010001111 #
b1111 $
b11 ,
b11 4
#261
b0000010010011100 #
b1100 $
b1001 %
b00 ,
b01 -
b01 0
b01 3
b00 4
b01 6
#262
b0000010010011101 #
b1101 $
b01 ,
b01 4
#263
b0000010010011110 #
b1110 $
b10 ,
b10 4
#264
b0000010010011111 #
b1111 $
b11 ,
b11 4
#265
b0000010010101100 #
b1100 $
b1010 %
b00 ,
b10 -
b10 0
b10 3
b00 4
b10 6
#266
b0000010010101101 #
b1101 $
b01 ,
b01 4
#267
b0000010010101110 #
b1110 $
b10 ,
b10 4
#268
b0000010010101111 #
b1111 $
b11 ,
b11 4
#269
b0000010010111100 #
b1100 $
b1011 %
b00 ,
b11 -
b11 0
b11 3
b00 4
b11 6
#270
b0000010010111101 #
b1101 $
b01 ,
b01 4
#271
b0000010010111110 #
b1110 $
b10 ,
b10 4
#272
b0000010010111111 #
b1111 $
b11 ,
b11 4
#273
b0000010110001100 #
b1100 $
b1000 %
b0101 &
b00 ,
b00 -
b01 .
b00 0
b01 2
b00 3
b00 4
b00 6
#274
b0000010110001101 #
b1101 $
b01 ,
b01 4
#275
b0000010110001110 #
b1110 $
b10 ,
b10 4
#276
b0000010110001111 #
b1111 $
b11 ,
b11 4
#277
b0000010110011100 #
b1100 $
b1001 %
b00 ,
b01 -
b01 0
b01 3
b00 4
b01 6
#278
b0000010110011101 #
b1101 $
b01 ,
b01 4
#279
b0000010110011110 #
b1110 $
b10 ,
b10 4
#280
b0000010110011111 #
b1111 $
b11 ,
b11 4
#281
b0000010110101100 #
b1100 $
b1010 %
b00 ,
b10 -
b10 0
b10 3
b00 4
b10 6
#282
b0000010110101101 #
b1101 $
b01 ,
b01 4
#283
b0000010110101110 #
b1110 $
b10 ,
b10 4
#284
b0000010110101111 #
b1111 $
b11 ,
b11 4
#285
b0000010110111100 #
b1100 $
b1011 %
b00 ,
b11 -
b11 0
b11 3
b00 4
b11 6
#286
b0000010110111101 #
b1101 $
b01 ,
b01 4
#287
b0000010110111110 #
b1110 $
b10 ,
b10 4
#288
b0000010110111111 #
b1111 $
b11 ,
b11 4
#289
b0000011010001100 #
b1100 $
b1000 %
b0110 &
b00 ,
b00 -
b10 .
b00 0
b10 2
b00 3
b00 4
b00 6
#290
b0000011010001101 #
b1101 $
b01 ,
b01 4
#291
b0000011010001110 #
b1110 $
b10 ,
b10 4
#292
b0000011010001111 #
b1111 $
b11 ,
b11 4
#293
b0000011010011100 #
b1100 $
b1001 %
b00 ,
b01 -
b01 0
b01 3
b00 4
b01 6
#294
b0000011010011101 #
b1101 $
b01 ,
b01 4
#295
b0000011010011110 #
b1110 $
b10 ,
b10 4
#296
b0000011010011111 #
b1111 $
b11 ,
b11 4
#297
b0000011010101100 #
b1100 $
b1010 %
b00 ,
b10 -
b10 0
b10 3
b00 4
b10 6
#298
b0000011010101101 #
b1101 $
b01 ,
b01 4
#299
b0000011010101110 #
b1110 $
b10 ,
b10 4
#300
b0000011010101111 #
b1111 $
b11 ,
b11 4
#301
b0000011010111100 #
b1100 $
b1011 %
b00 ,
b11 -
b11 0
b11 3
b00 4
b11 6
#302
b0000011010111101 #
b1101 $
b01 ,
b01 4
#303
b0000011010111110 #
b1110 $
b10 ,
b10 4
#304
b0000011010111111 #
b1111 $
b11 ,
b11 4
#305
b0000011110001100 #
b1100 $
b1000 %
b0111 &
b00 ,
b00 -
b11 .
b00 0
b11 2
b00 3
b00 4
b00 6
#306
b0000011110001101 #
b1101 $
b01 ,
b01 4
#307
b0000011110001110 #
b1110 $
b10 ,
b10 4
#308
b0000011110001111 #
b1111 $
b11 ,
b11 4
#309
b0000011110011100 #
b1100 $
b1001 %
b00 ,
b01 -
b01 0
b01 3
b00 4
b01 6
#310
b0000011110011101 #
b1101 $
b01 ,
b01 4
#311
b0000011110011110 #
b1110 $
b10 ,
b10 4
#312
b0000011110011111 #
b1111 $
b11 ,
b11 4
#313
b0000011110101100 #
b1100 $
b1010 %
b00 ,
b10 -
b10 0
b10 3
b00 4
b10 6
#314
b0000011110101101 #
b1101 $
b01 ,
b01 4
#315
b0000011110101110 #
b1110 $
b10 ,
b10 4
#316
b0000011110101111 #
b1111 $
b11 ,
b11 4
#317
b0000011110111100 #
b1100 $
b1011 %
b00 ,
b11 -
b11 0
b11 3
b00 4
b11 6
#318
b0000011110111101 #
b1101 $
b01 ,
b01 4
#319
b0000011110111110 #
b1110 $
b10 ,
b10 4
#320
b0000011110111111 #
b1111 $
b11 ,
b11 4
#321
b0001010010001100 #
b1100 $
b1000 %
b0100 &
b0001 '
b00 ,
b00 -
b00 .
b01 /
b00 0
b01 1
b00 2
b00 3
b00 4
b00 6
#322
b0001010010001101 #
b1101 $
b01 ,
b01 4
#323
b0001010010001110 #
b1110 $
b10 ,
b10 4
#324
b0001010010001111 #
b1111 $
b11 ,
b11 4
#325
b0001010010011100 #
b1100 $
b1001 %
b00 ,
b01 -
b01 0
b01 3
b00 4
b01 6
#326
b0001010010011101 #
b1101 $
b01 ,
b01 4
#327
b0001010010011110 #
b1110 $
b10 ,
b10 4
#328
b0001010010011111 #
b1111 $
b11 ,
b11 4
#329
b0001010010101100 #
b1100 $
b1010 %
b00 ,
b10 -
b10 0
b10 3
b00 4
b10 6
#330
b0001010010101101 #
b1101 $
b01 ,
b01 4
#331
b0001010010101110 #
b1110 $
b10 ,
b10 4
#332
b0001010010101111 #
b1111 $
b11 ,
b11 4
#333
b0001010010111100 #
b1100 $
b1011 %
b00 ,
b11 -
b11 0
b11 3
b00 4
b11 6
#334
b0001010010111101 #
b1101 $
b01 ,
b01 4
#335
b0001010010111110 #
b1110 $
b10 ,
b10 4
#336
b0001010010111111 #
b1111 $
b11 ,
b11 4
#337
b0001010110001100 #
b1100 $
b1000 %
b0101 &
b00 ,
b00 -
b01 .
b00 0
b01 2
b00 3
b00 4
b00 6
#338
b0001010110001101 #
b1101 $
b01 ,
b01 4
#339
b0001010110001110 #
b1110 $
b10 ,
b10 4
#340
b0001010110001111 #
b1111 $
b11 ,
b11 4
#341
b0001010110011100 #
b1100 $
b1001 %
b00 ,
b01 -
b01 0
b01 3
b00 4
b01 6
#342
b0001010110011101 #
b1101 $
b01 ,
b01 4
#343
b0001010110011110 #
b1110 $
b10 ,
b10 4
#344
b0001010110011111 #
b1111 $
b11 ,
b11 4
#345
b0001010110101100 #
b1100 $
b1010 %
b00 ,
b10 -
b10 0
b10 3
b00 4
b10 6
#346
b0001010110101101 #
b1101 $
b01 ,
b01 4
#347
b0001010110101110 #
b1110 $
b10 ,
b10 4
#348
b0001010110101111 #
b1111 $
b11 ,
b11 4
#349
b0001010110111100 #
b1100 $
b1011 %
b00 ,
b11 -
b11 0
b11 3
b00 4
b11 6
#350
b0001010110111101 #
b1101 $
b01 ,
b01 4
#351
b0001010110111110 #
b1110 $
b10 ,
b10 4
#352
b0001010110111111 #
b1111 $
b11 ,
b11 4
#353
b0001011010001100 #
b1100 $
b1000 %
b0110 &
b00 ,
b00 -
b10 .
b00 0
b10 2
b00 3
b00 4
b00 6
#354
b0001011010001101 #
b1101 $
b01 ,
b01 4
#355
b0001011010001110 #
b1110 $
b10 ,
b10 4
#356
b0001011010001111 #
b1111 $
b11 ,
b11 4
#357
b0001011010011100 #
b1100 $
b1001 %
b00 ,
b01 -
b01 0
b01 3
b00 4
b01 6
#358
b0001011010011101 #
b1101 $
b01 ,
b01 4
#359
b0001011010011110 #
b1110 $
b10 ,
b10 4
#360
b0001011010011111 #
b1111 $
b11 ,
b11 4
#361
b0001011010101100 #
b1100 $
b1010 %
b00 ,
b10 -
b10 0
b10 3
b00 4
b10 6
#362
b0001011010101101 #
b1101 $
b01 ,
b01 4
#363
b0001011010101110 #
b1110 $
b10 ,
b10 4
#364
b0001011010101111 #
b1111 $
b11 ,
b11 4
#365
b0001011010111100 #
b1100 $
b1011 %
b00 ,
b11 -
b11 0
b11 3
b00 4
b11 6
#366
b0001011010111101 #
b1101 $
b01 ,
b01 4
#367
b0001011010111110 #
b1110 $
b10 ,
b10 4
#368
b0001011010111111 #
b1111 $
b11 ,
b11 4
#369
b0001011110001100 #
b1100 $
b1000 %
b0111 &
b00 ,
b00 -
b11 .
b00 0
b11 2
b00 3
b00 4
b00 6
#370
b0001011110001101 #
b1101 $
b01 ,
b01 4
#371
b0001011110001110 #
b1110 $
b10 ,
b10 4
#372
b0001011110001111 #
b1111 $
b11 ,
b11 4
#373
b0001011110011100 #
b1100 $
b1001 %
b00 ,
b01 -
b01 0
b01 3
b00 4
b01 6
#374
b0001011110011101 #
b1101 $
b01 ,
b01 4
#375
b0001011110011110 #
b1110 $
b10 ,
b10 4
#376
b0001011110011111 #
b1111 $
b11 ,
b11 4
#377
b0001011110101100 #
b1100 $
b1010 %
b00 ,
b10 -
b10 0
b10 3
b00 4
b10 6
#378
b0001011110101101 #
b1101 $
b01 ,
b01 4
#379
b0001011110101110 #
b1110 $
b10 ,
b10 4
#380
b0001011110101111 #
b1111 $
b11 ,
b11 4
#381
b0001011110111100 #
b1100 $
b1011 %
b00 ,
b11 -
b11 0
b11 3
b00 4
b11 6
#382
b0001011110111101 #
b1101 $
b01 ,
b01 4
