de-encoder/decoder.v
module decoder (
    input  wire [2:0] x,
    input  wire       en,
    output reg  [6:0] y
); 
    always @(x or en) begin
        if (en) begin
            case(x)
                3'b001: y = 7'b111_1001;
                3'b010: y = 7'b010_0010;
                3'b011: y = 7'b011_0000;
                3'b100: y = 7'b001_1001;
                3'b101: y = 7'b001_0010;
                3'b110: y = 7'b000_0010;
                3'b111: y = 7'b111_1000;
                3'b000: y = 7'b111_1111;
            endcase
        end
        else y = 7'b000_0000;
    end
endmodule //decoder

de-encoder/wave.vcd
$version Generated by VerilatedVcd $end
$date Thu Oct  5 14:52:36 2023 $end
$timescale 1s $end

 $scope module TOP $end
  $var wire  1 $ en $end
  $var wire  3 # x [2:0] $end
  $var wire  7 % y [6:0] $end
  $scope module decoder $end
   $var wire  1 $ en $end
   $var wire  3 # x [2:0] $end
   $var wire  7 % y [6:0] $end
  $upscope $end
 $upscope $end
$enddefinitions $end


#1
b001 #
0$
b0000000 %
#2
b010 #
#3
b100 #
#4
b000 #
1$
b1111111 %
#5
b001 #
b1111001 %
#6
b010 #
b0100010 %
#7
b011 #
b0110000 %
#8
b100 #
b0011001 %
#9
b101 #
b0010010 %
#10
b110 #
b0000010 %
#11
b111 #
b1111000 %
