ALU/adder.v
module adder (
    input       [3:0] A,
    input       [3:0] B,
    input             op,
    output reg  [3:0] result,
    output reg        zero,
    output reg        overflow,
    output reg        carry    
);

wire [3:0] t_add_op;

assign t_add_op = ({4{op}}^B) ;
assign {carry, result} = A + t_add_op + {3'b0,op};
assign overflow = (A[3] == t_add_op[3]) && (result[3] != A[3]);
assign zero = ~(|result);

endmodule //adder

ALU/alu.v

module alu (
    input   [3:0] A,
    input   [3:0] B,
    input   [2:0] op,
    output  reg [3:0] out
);

    reg zero_add;
    reg zero_sub;
    reg zero_res;
    reg overflow;
    reg carry;
    reg [3:0] res;
    reg [3:0] sub;
    reg [3:0] add;

    adder u_add(.A(A),.B(B),.op(0),.result(add),.zero(zero_add),.carry(carry),.overflow(overflow));
    adder u_sub(.A(A),.B(B),.op(1),.result(sub),.zero(zero_sub),.carry(),.overflow());
    adder u_res(.A(A),.B(B),.op(1),.result(res),.zero(zero_res),.carry(),.overflow());
    always @(*) begin
        case(op)
            3'b000: out = add;
            3'b001: out = sub;
            3'b010: out = ~A;
            3'b011:out = A & B;
            3'b100:out = A | B;
            3'b101:out = A ^ B;
            3'b110:begin
                if(res[3] == 1)
                    out = 1;
                else 
                    out = 0;              
            end
            3'b111:begin
                if(zero_res == 1)
                    out = 1;
                else 
                    out = 0;              
            end
        endcase
    end

endmodule //alu

ALU/wave.vcd
$version Generated by VerilatedVcd $end
$date Thu Oct  5 23:28:13 2023 $end
$timescale 1s $end

 $scope module TOP $end
  $var wire  4 ' A [3:0] $end
  $var wire  4 ( B [3:0] $end
  $var wire  3 ) op [2:0] $end
  $var wire  4 * out [3:0] $end
  $scope module alu $end
   $var wire  4 ' A [3:0] $end
   $var wire  4 ( B [3:0] $end
   $var wire  4 & add [3:0] $end
   $var wire  1 , carry $end
   $var wire  3 ) op [2:0] $end
   $var wire  4 * out [3:0] $end
   $var wire  1 + overflow $end
   $var wire  4 % res [3:0] $end
   $var wire  4 % sub [3:0] $end
   $var wire  1 # zero_add $end
   $var wire  1 $ zero_res $end
   $var wire  1 $ zero_sub $end
   $scope module u_add $end
    $var wire  4 ' A [3:0] $end
    $var wire  4 ( B [3:0] $end
    $var wire  1 , carry $end
    $var wire  1 0 op $end
    $var wire  1 + overflow $end
    $var wire  4 & result [3:0] $end
    $var wire  4 ( t_add_op [3:0] $end
    $var wire  1 # zero $end
   $upscope $end
   $scope module u_res $end
    $var wire  4 ' A [3:0] $end
    $var wire  4 ( B [3:0] $end
    $var wire  1 . carry $end
    $var wire  1 1 op $end
    $var wire  1 - overflow $end
    $var wire  4 % result [3:0] $end
    $var wire  4 / t_add_op [3:0] $end
    $var wire  1 $ zero $end
   $upscope $end
   $scope module u_sub $end
    $var wire  4 ' A [3:0] $end
    $var wire  4 ( B [3:0] $end
    $var wire  1 . carry $end
    $var wire  1 1 op $end
    $var wire  1 - overflow $end
    $var wire  4 % result [3:0] $end
    $var wire  4 / t_add_op [3:0] $end
    $var wire  1 $ zero $end
   $upscope $end
  $upscope $end
 $upscope $end
$enddefinitions $end


#1
0#
0$
b1111 %
b1111 &
b0111 '
b1000 (
b000 )
b1111 *
0+
0,
1-
0.
b0111 /
00
11
#2
b001 )
#3
b010 )
b1000 *
#4
b011 )
b0000 *
#5
b100 )
b1111 *
#6
b101 )
#7
b110 )
b0001 *
#8
b111 )
b0000 *
