shift/LFSR.v
module LFSR (
    input        clk,
    input        rst_n,
    input  [7:0] seed,
    input        start, 
    output [7:0] dout,
    output       dout_vld
);

    reg [7:0] cnt;
    reg       start_r;
    wire      start_pedge;
    wire      xor_bit;

    always @(posedge clk or negedge rst_n) begin
      if(!rst_n)
        begin
          start_r <= 0 ;
        end
        else begin
          start_r <= start;
        end
    end

    assign start_pedge = start & ~start_r;

    always @(posedge clk or negedge rst_n) begin
      if(!rst_n)
        begin
          cnt <= 0;
        end
        else if(start_pedge)begin
          cnt <= seed;
        end
        else begin
            cnt <= {xor_bit,cnt[7:1]};
        end
    end

    assign xor_bit = cnt[0]^cnt[2]^cnt[3]^cnt[4];

    assign dout = cnt;
    assign dout_vld = start_r && cnt == seed;

endmodule //LFSR

shift/wave.vcd
$version Generated by VerilatedVcd $end
$date Sat Oct  7 21:52:46 2023 $end
$timescale 1s $end

 $scope module TOP $end
  $var wire  1 & clk $end
  $var wire  8 * dout [7:0] $end
  $var wire  1 + dout_vld $end
  $var wire  1 ' rst_n $end
  $var wire  8 ( seed [7:0] $end
  $var wire  1 ) start $end
  $scope module LFSR $end
   $var wire  1 & clk $end
   $var wire  8 # cnt [7:0] $end
   $var wire  8 * dout [7:0] $end
   $var wire  1 + dout_vld $end
   $var wire  1 ' rst_n $end
   $var wire  8 ( seed [7:0] $end
   $var wire  1 ) start $end
   $var wire  1 , start_pedge $end
   $var wire  1 $ start_r $end
   $var wire  1 % xor_bit $end
  $upscope $end
 $upscope $end
$enddefinitions $end


#1
b00000000 #
0$
0%
1&
0'
b00000000 (
0)
b00000000 *
0+
0,
#2
#3
#4
#5
#6
0&
#7
#8
#9
#10
#11
b10011110 #
1$
1%
1&
1'
b10011110 (
1)
b10011110 *
1+
#12
#13
#14
#15
#16
0&
#17
#18
#19
#20
#21
b11001111 #
1&
b11001111 *
0+
#22
#23
#24
#25
#26
0&
#27
#28
#29
#30
#31
b11100111 #
0%
1&
b11100111 *
#32
#33
#34
#35
#36
0&
#37
#38
#39
#40
#41
b01110011 #
1&
b01110011 *
#42
#43
#44
#45
#46
0&
#47
#48
#49
#50
#51
b00111001 #
1%
1&
b00111001 *
#52
#53
#54
#55
#56
0&
#57
#58
#59
#60
#61
b10011100 #
1&
b10011100 *
#62
#63
#64
#65
#66
0&
#67
#68
#69
#70
#71
b11001110 #
0%
1&
b11001110 *
#72
#73
#74
#75
#76
0&
#77
#78
#79
#80
#81
b01100111 #
1&
b01100111 *
#82
#83
#84
#85
#86
0&
#87
#88
#89
#90
#91
b00110011 #
1&
b00110011 *
#92
#93
#94
#95
#96
0&
#97
#98
#99
#100
#101
b00011001 #
1%
1&
b00011001 *
#102
#103
#104
#105
#106
0&
#107
#108
#109
#110
#111
b10001100 #
0%
1&
b10001100 *
#112
#113
#114
#115
#116
0&
#117
#118
#119
#120
#121
b01000110 #
1%
1&
b01000110 *
#122
#123
#124
#125
#126
0&
#127
#128
#129
#130
#131
b10100011 #
1&
b10100011 *
#132
#133
#134
#135
#136
0&
#137
#138
#139
#140
#141
b11010001 #
0%
1&
b11010001 *
#142
#143
#144
#145
#146
0&
#147
#148
#149
#150
#151
b01101000 #
1%
1&
b01101000 *
#152
#153
#154
#155
#156
0&
#157
#158
#159
#160
#161
b10110100 #
0%
1&
b10110100 *
#162
#163
#164
#165
#166
0&
#167
#168
#169
#170
#171
b01011010 #
1&
b01011010 *
#172
#173
#174
#175
#176
0&
#177
#178
#179
#180
#181
b00101101 #
1%
1&
b00101101 *
#182
#183
#184
#185
#186
0&
#187
#188
#189
#190
#191
b10010110 #
0%
1&
b10010110 *
#192
#193
#194
#195
#196
0&
#197
#198
#199
#200
#201
b01001011 #
1&
b01001011 *
#202
#203
#204
#205
#206
0&
#207
#208
#209
#210
#211
b00100101 #
1&
b00100101 *
#212
#213
#214
#215
#216
0&
#217
#218
#219
#220
#221
b00010010 #
1%
1&
b00010010 *
#222
#223
#224
#225
#226
0&
#227
#228
#229
#230
#231
b10001001 #
0%
1&
b10001001 *
#232
#233
#234
#235
#236
0&
#237
#238
#239
#240
#241
b01000100 #
1%
1&
b01000100 *
#242
#243
#244
#245
#246
0&
#247
#248
#249
#250
#251
b10100010 #
0%
1&
b10100010 *
#252
#253
#254
#255
#256
0&
#257
#258
#259
#260
#261
b01010001 #
1&
b01010001 *
#262
#263
#264
#265
#266
0&
#267
#268
#269
#270
#271
b00101000 #
1%
1&
b00101000 *
#272
#273
#274
#275
#276
0&
#277
#278
#279
#280
#281
b10010100 #
0%
1&
b10010100 *
#282
#283
#284
#285
#286
0&
#287
#288
#289
#290
#291
b01001010 #
1%
1&
b01001010 *
#292
#293
#294
#295
#296
0&
#297
#298
#299
#300
#301
b10100101 #
0%
1&
b10100101 *
#302
#303
#304
#305
#306
0&
#307
#308
#309
#310
#311
b01010010 #
1%
1&
b01010010 *
#312
#313
#314
#315
#316
0&
#317
#318
#319
#320
#321
b10101001 #
0%
1&
b10101001 *
#322
#323
#324
#325
#326
0&
#327
#328
#329
#330
#331
b01010100 #
1&
b01010100 *
#332
#333
#334
#335
#336
0&
#337
#338
#339
#340
#341
b00101010 #
1%
1&
b00101010 *
#342
#343
#344
#345
#346
0&
#347
#348
#349
#350
#351
b10010101 #
1&
b10010101 *
#352
#353
#354
#355
#356
0&
#357
#358
#359
#360
#361
b11001010 #
1&
b11001010 *
#362
#363
#364
#365
#366
0&
#367
#368
#369
#370
#371
b11100101 #
0%
1&
b11100101 *
#372
#373
#374
#375
#376
0&
#377
#378
#379
#380
#381
b01110010 #
1%
1&
b01110010 *
#382
#383
#384
#385
#386
0&
#387
#388
#389
#390
#391
b10111001 #
1&
b10111001 *
#392
#393
#394
#395
#396
0&
#397
#398
#399
#400
#401
b11011100 #
1&
b11011100 *
#402
#403
#404
#405
#406
0&
#407
#408
#409
#410
#411
b11101110 #
0%
1&
b11101110 *
#412
#413
#414
#415
#416
0&
#417
#418
#419
#420
#421
b01110111 #
1%
1&
b01110111 *
#422
#423
#424
#425
#426
0&
#427
#428
#429
#430
#431
b10111011 #
1&
b10111011 *
#432
#433
#434
#435
#436
0&
#437
#438
#439
#440
#441
b11011101 #
0%
1&
b11011101 *
#442
#443
#444
#445
#446
0&
#447
#448
#449
#450
#451
b01101110 #
1&
b01101110 *
#452
#453
#454
#455
#456
0&
#457
#458
#459
#460
#461
b00110111 #
1%
1&
b00110111 *
#462
#463
#464
#465
#466
0&
#467
#468
#469
#470
#471
b10011011 #
1&
b10011011 *
#472
#473
#474
#475
#476
0&
#477
#478
#479
#480
#481
b11001101 #
1&
b11001101 *
#482
#483
#484
#485
#486
0&
#487
#488
#489
#490
#491
b11100110 #
1&
b11100110 *
#492
#493
#494
#495
#496
0&
#497
#498
#499
#500
#501
b11110011 #
0$
0%
1&
0)
b11110011 *
#502
#503
#504
#505
#506
0&
#507
#508
#509
#510
#511
b01111001 #
1%
1&
b01111001 *
#512
#513
#514
#515
#516
0&
#517
#518
#519
#520
#521
b10111100 #
1&
b10111100 *
#522
#523
#524
#525
#526
0&
#527
#528
#529
#530
#531
b11011110 #
1&
b11011110 *
#532
#533
#534
#535
#536
0&
#537
#538
#539
#540
#541
b11101111 #
1&
b11101111 *
#542
#543
#544
#545
#546
0&
#547
#548
#549
#550
#551
b11110111 #
1&
b11110111 *
#552
#553
#554
#555
#556
0&
#557
#558
#559
#560
#561
b11111011 #
1&
b11111011 *
#562
#563
#564
#565
#566
0&
#567
#568
#569
#570
#571
b11111101 #
0%
1&
b11111101 *
#572
#573
#574
#575
#576
0&
#577
#578
#579
#580
#581
b01111110 #
1%
1&
b01111110 *
#582
#583
#584
#585
#586
0&
#587
#588
#589
#590
#591
b10111111 #
0%
1&
b10111111 *
#592
#593
#594
#595
#596
0&
#597
#598
#599
#600
#601
b01011111 #
1&
b01011111 *
#602
#603
#604
#605
#606
0&
#607
#608
#609
#610
#611
b00101111 #
1%
1&
b00101111 *
#612
#613
#614
#615
#616
0&
#617
#618
#619
#620
#621
b10010111 #
1&
b10010111 *
#622
#623
#624
#625
#626
0&
#627
#628
#629
#630
#631
b11001011 #
0%
1&
b11001011 *
#632
#633
#634
#635
#636
0&
#637
#638
#639
#640
#641
b01100101 #
1&
b01100101 *
#642
#643
#644
#645
#646
0&
#647
#648
#649
#650
#651
b00110010 #
1%
1&
b00110010 *
#652
#653
#654
#655
#656
0&
#657
#658
#659
#660
#661
b10011001 #
1&
b10011001 *
#662
#663
#664
#665
#666
0&
#667
#668
#669
#670
#671
b11001100 #
0%
1&
b11001100 *
#672
#673
#674
#675
#676
0&
#677
#678
#679
#680
#681
b01100110 #
1%
1&
b01100110 *
#682
#683
#684
#685
#686
0&
#687
#688
#689
#690
#691
b10110011 #
0%
1&
b10110011 *
#692
#693
#694
#695
#696
0&
#697
#698
#699
#700
#701
b01011001 #
1%
1&
b01011001 *
#702
#703
#704
#705
#706
0&
#707
#708
#709
#710
#711
b10101100 #
0%
1&
b10101100 *
#712
#713
#714
#715
#716
0&
#717
#718
#719
#720
#721
b01010110 #
1&
b01010110 *
#722
#723
#724
#725
#726
0&
#727
#728
#729
#730
#731
b00101011 #
1&
b00101011 *
#732
#733
#734
#735
#736
0&
#737
#738
#739
#740
#741
b00010101 #
1%
1&
b00010101 *
#742
#743
#744
#745
#746
0&
#747
#748
#749
#750
#751
b10001010 #
1&
b10001010 *
#752
#753
#754
#755
#756
0&
#757
#758
#759
#760
#761
b11000101 #
0%
1&
b11000101 *
#762
#763
#764
#765
#766
0&
#767
#768
#769
#770
#771
b01100010 #
1&
b01100010 *
#772
#773
#774
#775
#776
0&
#777
#778
#779
#780
#781
b00110001 #
1&
b00110001 *
#782
#783
#784
#785
#786
0&
#787
#788
#789
#790
#791
b00011000 #
1&
b00011000 *
#792
#793
#794
#795
#796
0&
#797
#798
#799
#800
#801
b00001100 #
1&
b00001100 *
#802
#803
#804
#805
#806
0&
#807
#808
#809
#810
#811
b00000110 #
1%
1&
b00000110 *
#812
#813
#814
#815
#816
0&
#817
#818
#819
#820
#821
b10000011 #
1&
b10000011 *
#822
#823
#824
#825
#826
0&
#827
#828
#829
#830
#831
b11000001 #
1&
b11000001 *
#832
#833
#834
#835
#836
0&
#837
#838
#839
#840
#841
b11100000 #
0%
1&
b11100000 *
#842
#843
#844
#845
#846
0&
#847
#848
#849
#850
#851
b01110000 #
1%
1&
b01110000 *
#852
#853
#854
#855
#856
0&
#857
#858
#859
#860
#861
b10111000 #
0%
1&
b10111000 *
#862
#863
#864
#865
#866
0&
#867
#868
#869
#870
#871
b01011100 #
1%
1&
b01011100 *
#872
#873
#874
#875
#876
0&
#877
#878
#879
#880
#881
b10101110 #
0%
1&
b10101110 *
#882
#883
#884
#885
#886
0&
#887
#888
#889
#890
#891
b01010111 #
1%
1&
b01010111 *
#892
#893
#894
#895
#896
0&
#897
#898
#899
#900
#901
b10101011 #
0%
1&
b10101011 *
#902
#903
#904
#905
#906
0&
#907
#908
#909
#910
#911
b01010101 #
1%
1&
b01010101 *
#912
#913
#914
#915
#916
0&
#917
#918
#919
#920
#921
b10101010 #
1&
b10101010 *
#922
#923
#924
#925
#926
0&
#927
#928
#929
#930
#931
b11010101 #
1&
b11010101 *
#932
#933
#934
#935
#936
0&
#937
#938
#939
#940
#941
b11101010 #
1&
b11101010 *
#942
#943
#944
#945
#946
0&
#947
#948
#949
#950
#951
b11110101 #
1&
b11110101 *
#952
#953
#954
#955
#956
0&
#957
#958
#959
#960
#961
b11111010 #
0%
1&
b11111010 *
#962
#963
#964
#965
#966
0&
#967
#968
#969
#970
#971
b01111101 #
1&
b01111101 *
#972
#973
#974
#975
#976
0&
#977
#978
#979
#980
#981
b00111110 #
1%
1&
b00111110 *
#982
#983
#984
#985
#986
0&
#987
#988
#989
#990
#991
b10011111 #
0%
1&
b10011111 *
